{
  "Marguerite.Boissonneau": {
    "first_name": "Marguerite",
    "last_name": "Boissonneau",
    "gender": "F",
    "relationship": {
      "Jean-François.Tanguay": { "type": "union" }
    },
    "source": "https://www.myheritage.fr/site-family-tree-205814691/charest"
  },
  "Jean-François.Tanguay": {
    "first_name": "Jean-François",
    "last_name": "Tanguay",
    "gender": "M",
    "relationship": {
      "Marguerite.Boissonneau": { "type": "union" }
    },
    "source": "https://www.myheritage.fr/site-family-tree-205814691/charest"
  }
}
