{
  "Geneviève.Giroux": {
    "first_name": "Geneviève",
    "last_name": "Giroux",
    "gender": "F",
    "relationship": {
      "Thérèse.Jolivet": { "type": "mother" },
      "Jean-Baptiste.Giroux": { "type": "father" },
      "Jean-Baptiste3.Chorret Chaurette": { "type": "union" }
    },
    "source": "data/Simon Charest.pdf"
  },
  "Jean-Baptiste3.Chorret Chaurette": {
    "first_name": "Jean-Baptiste",
    "last_name": "Chorret Chaurette",
    "gender": "M",
    "relationship": {
	  "Marie-Catherine.Letourneux": { "type": "mother" },
      "Jean-Baptiste2.Choret Chaurette": { "type": "father" },
      "Geneviève.Giroux": { "type": "union" }
    },
    "source": "data/Simon Charest.pdf"
  },
  "Théodore.Choret Chaurette": {
    "first_name": "Théodore",
    "last_name": "Choret Chaurette",
    "gender": "M",
    "relationship": {
      "Geneviève.Giroux": { "type": "mother" },
      "Jean-Baptiste3.Chorret Chaurette": { "type": "father" },
      "Josephte.Valiquette": { "type": "union" }
    },
    "source": "data/Simon Charest.pdf"
  },
  "Josephte.Valiquette": {
    "first_name": "Josephte",
    "last_name": "Valiquette",
    "gender": "F",
    "relationship": {
      "Théodore.Choret Chaurette": { "type": "union" }
    },
    "source": "data/Simon Charest.pdf"
  },
  "Josephte.Éthier": {
    "first_name": "Josephte",
    "last_name": "Éthier",
    "gender": "F",
    "relationship": {
      "Josephte.Biroleau": { "type": "mother" },
      "Pierre.Éthier": { "type": "father" },
      "Jacques.Demers": { "type": "union" }
    },
    "source": "data/Simon Charest.pdf"
  },
  "Jacques.Demers": {
    "first_name": "Jacques",
    "last_name": "Demers",
    "gender": "M",
    "relationship": {
      "Ursule.Beaulne": { "type": "mother" },
      "Jean-Baptiste.Demers": { "type": "father" },
      "Josephte.Éthier": { "type": "union" }
    },
    "source": "data/Simon Charest.pdf"
  },
  "Marie-Catherine Théotiste.Morin": {
    "first_name": "Marie-Catherine Théotiste",
    "last_name": "Morin",
    "gender": "F",
    "relationship": {
      "Jean-Baptiste.Tanguay": { "type": "union" }
    },
    "source": "https://www.myheritage.fr/site-family-tree-205814691/charest"
  },
  "Jean-Baptiste.Tanguay": {
    "first_name": "Jean-Baptiste",
    "last_name": "Tanguay",
    "gender": "M",
    "relationship": {
      "Marguerite.Boissonneau": { "type": "mother" },
      "Jean-François.Tanguay": { "type": "father" },
      "Marie-Catherine Théotiste.Morin": { "type": "union" }
    },
    "source": "https://www.myheritage.fr/site-family-tree-205814691/charest"
  }
}
